README.md
setup.cfg
setup.py
localstack_extension_outages.egg-info/PKG-INFO
localstack_extension_outages.egg-info/SOURCES.txt
localstack_extension_outages.egg-info/dependency_links.txt
localstack_extension_outages.egg-info/entry_points.txt
localstack_extension_outages.egg-info/not-zip-safe
localstack_extension_outages.egg-info/requires.txt
localstack_extension_outages.egg-info/top_level.txt
outages/__init__.py
outages/config.py
outages/constants.py
outages/exceptions.py
outages/extension.py
outages/handlers.py
outages/routes.py