Metadata-Version: 2.1
Name: localstack-extension-outages
Version: 0.4.2
Summary: LocalStack Extension: Outages
Home-page: https://localstack.cloud
Author: LocalStack
Author-email: support@localstack.cloud
Requires-Dist: jsonschema>=4.18
Provides-Extra: dev
Requires-Dist: black>=22.3.0; extra == "dev"
Requires-Dist: flake8>=6.0.0; extra == "dev"
Requires-Dist: isort>=5.12.0; extra == "dev"
Requires-Dist: localstack>=3.0.0.post2; extra == "dev"
Requires-Dist: localstack-core[runtime]>=3.0.0; extra == "dev"
Requires-Dist: localstack-ext>=3.0.0.post2; extra == "dev"
Requires-Dist: localstack-obfuscator>=0.2.0; extra == "dev"
Requires-Dist: pyproject-flake8>=6.0.0.post1; extra == "dev"
Provides-Extra: test
Requires-Dist: botocore>=1.31.2; extra == "test"
Requires-Dist: boto3>=1.26.121; extra == "test"
Requires-Dist: pytest~=6.2; extra == "test"
